pyresolve/__init__.py
pyresolve-1.1.0.dist-info/LICENSE
pyresolve-1.1.0.dist-info/METADATA
pyresolve-1.1.0.dist-info/WHEEL
pyresolve-1.1.0.dist-info/top_level.txt
pyresolve-1.1.0.dist-info/RECORD
