Metadata-Version: 2.1
Name: pyresolve
Version: 1.1.0
Summary: Resolve dot notation from dictionary
Home-page: https://github.com/fiverr/pyresolve
Author: fiverr
Author-email: devops@fiverr.com
License: MIT
Platform: UNKNOWN
Classifier: Programming Language :: Python
Classifier: Operating System :: OS Independent
Requires-Python: >=2
